src/__init__.py
src/test_ibbuploader.py
src/uploader.py
IbbUploader-0.0.1.dist-info/METADATA
IbbUploader-0.0.1.dist-info/WHEEL
IbbUploader-0.0.1.dist-info/top_level.txt
IbbUploader-0.0.1.dist-info/RECORD
