Metadata-Version: 2.1
Name: IbbUploader
Version: 0.0.1
Summary: A Python library for uploading images to ImgBB via their API.
Home-page: https://github.com/dlrodev92/ibb_uploader_python
Author: dlrodev92
Author-email: dlrdev92@gmail.com
Project-URL: Bug Reports, https://github.com/dlrodev92/ibb_uploader_python/issues
Project-URL: Source, https://github.com/dlrodev92/ibb_uploader_python
Classifier: Development Status :: 3 - Alpha
Classifier: Intended Audience :: Developers
Classifier: Topic :: Software Development :: Build Tools
Classifier: License :: OSI Approved :: MIT License
Classifier: Programming Language :: Python :: 3
Classifier: Programming Language :: Python :: 3.7
Classifier: Programming Language :: Python :: 3.8
Classifier: Programming Language :: Python :: 3.9
Classifier: Programming Language :: Python :: 3.10
Classifier: Programming Language :: Python :: 3.11
Classifier: Operating System :: OS Independent
Requires-Python: >=3.6
Requires-Dist: requests
